README.md
pyproject.toml
setup.cfg
setup.py
lyncs/__init__.py
lyncs/lattice.py
lyncs.egg-info/PKG-INFO
lyncs.egg-info/SOURCES.txt
lyncs.egg-info/dependency_links.txt
lyncs.egg-info/requires.txt
lyncs.egg-info/top_level.txt
lyncs/field/__init__.py
lyncs/field/array.py
lyncs/field/base.py
lyncs/field/contractions.py
lyncs/field/random.py
lyncs/field/reductions.py
lyncs/field/ufuncs.py
lyncs/field/types/__init__.py
lyncs/field/types/base.py
lyncs/field/types/generic.py
lyncs/field/types/quantum.py
lyncs/io/__init__.py
lyncs/io/base.py
lyncs/io/lime/__init__.py
lyncs/io/lime/lime.py
test/__init__.py
test/test_lattice.py
test/test_lime.py
test/field/test_array.py
test/field/test_base.py
test/field/test_numpy.py