Metadata-Version: 2.1
Name: lyncs
Version: 0.0.3
Summary: A python API for Lattice QCD applications
Home-page: https://lyncs-api.github.io
Author: Simone Bacchio
Author-email: s.bacchio@gmail.com
License: UNKNOWN
Download-URL: https://github.com/Lyncs-API/lyncs
Keywords: python,Lattice,QCD,API,applications
Platform: UNKNOWN
Classifier: Development Status :: 2 - Pre-Alpha
Classifier: Intended Audience :: Developers
Classifier: Intended Audience :: Education
Classifier: Intended Audience :: Science/Research
Classifier: License :: OSI Approved :: BSD License
Classifier: Natural Language :: English
Classifier: Operating System :: Unix
Classifier: Programming Language :: C
Classifier: Programming Language :: C++
Classifier: Programming Language :: Python :: 3 :: Only
Classifier: Topic :: Scientific/Engineering :: Physics
Provides-Extra: dask
Provides-Extra: clime
Provides-Extra: DDalphaAMG
Provides-Extra: test
Provides-Extra: io
Provides-Extra: mpi
Provides-Extra: notebook
Provides-Extra: all
